CHANGES.txt
MANIFEST.in
README.rst
setup.py
docs/INSTALL.txt
docs/LICENSE.GPL
docs/LICENSE.txt
wildcard/__init__.py
wildcard.fixpersistentutilities.egg-info/PKG-INFO
wildcard.fixpersistentutilities.egg-info/SOURCES.txt
wildcard.fixpersistentutilities.egg-info/dependency_links.txt
wildcard.fixpersistentutilities.egg-info/entry_points.txt
wildcard.fixpersistentutilities.egg-info/namespace_packages.txt
wildcard.fixpersistentutilities.egg-info/not-zip-safe
wildcard.fixpersistentutilities.egg-info/requires.txt
wildcard.fixpersistentutilities.egg-info/top_level.txt
wildcard/fixpersistentutilities/__init__.py
wildcard/fixpersistentutilities/classfactory.py
wildcard/fixpersistentutilities/configure.zcml
wildcard/fixpersistentutilities/tests.py
wildcard/fixpersistentutilities/views.py
wildcard/fixpersistentutilities/templates/confirm.pt
wildcard/fixpersistentutilities/templates/fix-interfaces.pt
wildcard/fixpersistentutilities/templates/manage-utilities.pt