Metadata-Version: 1.0
Name: wildcard.fixpersistentutilities
Version: 1.1b5
Summary: a package that can help you remove local persistent utilies
Home-page: https://github.com/collective/wildcard.fixpersistentutilities/
Author: Nathan Van Gheem
Author-email: nathan.vangheem@wildcardcorp.com
License: GPL
Platform: UNKNOWN
Classifier: Framework :: Plone
Classifier: Programming Language :: Python
